{
    "name": "Matcha Gotcha",
    "class": "CLASS_SPECIAL",
    "type": "TYPE_GRASS",
    "power": 80,
    "accuracy": 90,
    "pp": 15,
    "effect": {
        "type": "BATTLE_EFFECT_HIT",
        "chance": 20
    },
    "range": "RANGE_ADJACENT_OPPONENTS",
    "priority": 0,
    "flags": [
        "MOVE_FLAG_CAN_PROTECT",
        "MOVE_FLAG_CAN_MIRROR_MOVE",
        "MOVE_FLAG_TRIGGERS_KINGS_ROCK"
    ],
    "contest": {
        "effect": "CONTEST_EFFECT_NONE",
        "type": "CONTEST_TYPE_COOL"
    }
}