{
  "base_stats": {
    "hp": 35,
    "attack": 41,
    "defense": 45,
    "speed": 20,
    "special_attack": 29,
    "special_defense": 40
  },
  "types": [
    "TYPE_BUG",
    "TYPE_BUG"
  ],
  "catch_rate": 255,
  "base_exp_reward": 42,
  "ev_yields": {
    "hp": 0,
    "attack": 0,
    "defense": 1,
    "speed": 0,
    "special_attack": 0,
    "special_defense": 0
  },
  "held_items": {
    "common": "ITEM_NONE",
    "rare": "ITEM_NONE"
  },
  "gender_ratio": "GENDER_RATIO_FEMALE_50",
  "hatch_cycles": 15,
  "base_friendship": 50,
  "exp_rate": "EXP_RATE_ERRATIC",
  "egg_groups": [
    "EGG_GROUP_BUG",
    "EGG_GROUP_BUG"
  ],
  "abilities": [
    "ABILITY_INSOMNIA",
    "ABILITY_NONE"
  ],
  "safari_flee_rate": 0,
  "body_color": "MON_COLOR_WHITE",
  "flip_sprite": false,
  "icon_palette": 1,
  "learnset": {
    "by_level": [
      [
        1,
        "MOVE_STRING_SHOT"
      ],
      [
        1,
        "MOVE_TACKLE"
      ],
      [
        5,
        "MOVE_STRUGGLEBUG"
      ],
      [
        8,
        "MOVE_ASSURANCE"
      ],
      [
        11,
        "MOVE_FEINT"
      ],
      [
        14,
        "MOVE_BUG_BITE"
      ],
      [
        18,
        "MOVE_BLOCK"
      ],
      [
        22,
        "MOVE_COUNTER"
      ],
      [
        25,
        "MOVE_HEADBUTT"
      ],
      [
        29,
        "MOVE_STICKYWEB"
      ],
      [
        33,
        "MOVE_GASTRO_ACID"
      ],
      [
        36,
        "MOVE_CIRCLETHROW"
      ],
      [
        40,
        "MOVE_THROATCHOP"
      ],
      [
        44,
        "MOVE_SKITTERSMACK"
      ]
    ],
    "by_tm": [],
    "by_tutor": [],
    "egg_moves": []
  },
  "evolutions": [],
  "offspring": "SPECIES_TAROUNTULA",
  "footprint": {
    "has": true,
    "size": "FOOTPRINT_MEDIUM",
    "type": "FOOTPRINT_TYPE_CUTE"
  },
  "pokedex_data": {
    "height": 3,
    "weight": 40,
    "body_shape": "SHAPE_QUADRUPED",
    "trainer_scale_f": 256,
    "pokemon_scale_f": 256,
    "trainer_scale_m": 256,
    "pokemon_scale_m": 256,
    "trainer_pos_f": 0,
    "pokemon_pos_f": 0,
    "trainer_pos_m": 0,
    "pokemon_pos_m": 0,
    "en": {
      "name": "TAROUNTULA",
      "category": "String Ball Pok\u00e9mon",
      "entry_text": [
        "The ball of threads wrapped around its body is elastic enough to deflect the scythes of Scyther, this Pok\u00e9mon’s natural enemy."
      ]
    },
    "fr": {
      "name": "TAROUNTULA",
      "category": "String Ball Pok\u00e9mon",
      "entry_text": [
        "The ball of threads wrapped around its body is elastic enough to deflect the scythes of Scyther, this Pok\u00e9mon’s natural enemy."
      ]
    },
    "de": {
      "name": "TAROUNTULA",
      "category": "String Ball Pok\u00e9mon",
      "entry_text": [
        "The ball of threads wrapped around its body is elastic enough to deflect the scythes of Scyther, this Pok\u00e9mon’s natural enemy."
      ]
    },
    "it": {
      "name": "TAROUNTULA",
      "category": "String Ball Pok\u00e9mon",
      "entry_text": [
        "The ball of threads wrapped around its body is elastic enough to deflect the scythes of Scyther, this Pok\u00e9mon’s natural enemy."
      ]
    },
    "es": {
      "name": "TAROUNTULA",
      "category": "String Ball Pok\u00e9mon",
      "entry_text": [
        "The ball of threads wrapped around its body is elastic enough to deflect the scythes of Scyther, this Pok\u00e9mon’s natural enemy."
      ]
    },
    "jp": {
      "name": "TAROUNTULA",
      "category": "String Ball Pok\u00e9mon",
      "entry_text": [
        "The ball of threads wrapped around its body is elastic enough to deflect the scythes of Scyther, this Pok\u00e9mon’s natural enemy."
      ]
    }
  },
  "catching_show": {
    "pal_park_land_area": "PAL_PARK_AREA_LAND_NONE",
    "pal_park_water_area": "PAL_PARK_AREA_WATER_NONE",
    "catching_points": 50,
    "rarity": 30,
    "unused": 0
  }
}
